{
    "logo": "https://baguettery-alt.chaos-branding-tool.pages.dev/media/chaos/source_mw.svg",
    "icon": "https://baguettery-alt.chaos-branding-tool.pages.dev/media/chaos/square_mw.svg",
    "name": "Chaos Engine",
    "color": "#b92f2f",
    "categories": [
        {
            "label": "Chaotic general",
            "id": "general",
            "home": "vscript",
            "topics": [
                {
                    "id": "vscript",
                    "name": "Vscript"
                },
                {
                    "id": "modding",
                    "name": "Modding"
                }
            ]
        },
        {
            "label": "Less chaotic general",
            "id": "less-general",
            "home": "panorama",
            "topics": [
                {
                    "id": "panorama",
                    "name": "Pano"
                }
            ]
        }
    ],
    "features": ["BE_CHAOTIC"]
}
